gh_pr_rev_md/__init__.py
gh_pr_rev_md/cli.py
gh_pr_rev_md/config.py
gh_pr_rev_md/formatter.py
gh_pr_rev_md/git_utils.py
gh_pr_rev_md/github_client.py
gh_pr_rev_md-0.1.0.dist-info/licenses/LICENSE
gh_pr_rev_md-0.1.0.dist-info/METADATA
gh_pr_rev_md-0.1.0.dist-info/WHEEL
gh_pr_rev_md-0.1.0.dist-info/entry_points.txt
gh_pr_rev_md-0.1.0.dist-info/top_level.txt
gh_pr_rev_md-0.1.0.dist-info/RECORD
