Metadata-Version: 2.4
Name: gh-pr-rev-md
Version: 0.1.0
Summary: CLI tool to fetch GitHub PR review comments and format as markdown
Author-email: Peter Souter <p.morsou+pypi@gmail.com>
License: MIT
Project-URL: Homepage, https://github.com/petems/gh-pr-rev-md
Project-URL: Repository, https://github.com/petems/gh-pr-rev-md
Project-URL: Issues, https://github.com/petems/gh-pr-rev-md/issues
Keywords: github,pull-request,review,cli,markdown
Classifier: Development Status :: 4 - Beta
Classifier: Intended Audience :: Developers
Classifier: License :: OSI Approved :: MIT License
Classifier: Programming Language :: Python :: 3
Classifier: Programming Language :: Python :: 3.9
Classifier: Programming Language :: Python :: 3.10
Classifier: Programming Language :: Python :: 3.11
Classifier: Programming Language :: Python :: 3.12
Classifier: Topic :: Software Development :: Version Control :: Git
Classifier: Topic :: Utilities
Requires-Python: >=3.9
License-File: LICENSE
Requires-Dist: click>=8.0.0
Requires-Dist: requests>=2.25.0
Requires-Dist: PyYAML>=6.0
Provides-Extra: dev
Requires-Dist: bandit[sarif]>=1.8.6; extra == "dev"
Requires-Dist: pytest>=7.0.0; extra == "dev"
Requires-Dist: pytest-cov>=4.0.0; extra == "dev"
Requires-Dist: pytest-xdist>=3.5.0; extra == "dev"
Requires-Dist: pytest-randomly>=3.15.0; extra == "dev"
Requires-Dist: ruff>=0.5.0; extra == "dev"
Requires-Dist: sphinx>=7.0.0; extra == "dev"
Requires-Dist: sphinx-rtd-theme>=2.0.0; extra == "dev"
Dynamic: license-file
